LICENSE
MANIFEST.in
README.md
cv_parser
setup.py
cv_parser.egg-info/PKG-INFO
cv_parser.egg-info/SOURCES.txt
cv_parser.egg-info/dependency_links.txt
cv_parser.egg-info/requires.txt
cv_parser.egg-info/top_level.txt
example/me.jpg
example/my_cv.yml
renderers/__init__.py
renderers/pdf/__init__.py
renderers/pdf/render.py
renderers/pdf/resources/PTSans-Bold.ttf
renderers/pdf/resources/PTSans-Italic.ttf
renderers/pdf/resources/PTSans-Regular.ttf
renderers/pdf/resources/Questrial-Regular.ttf
renderers/web/__init__.py
renderers/web/render.py
renderers/web/templates/education.html
renderers/web/templates/events.html
renderers/web/templates/experience.html
renderers/web/templates/footer.html
renderers/web/templates/header.html
renderers/web/templates/hobbies.html
renderers/web/templates/languages.html
renderers/web/templates/main.html
renderers/web/templates/references.html
renderers/web/templates/skills.html
renderers/web/themes/default/css/main.css
renderers/web/themes/default/css/normalize.css
renderers/web/themes/default/js/main.js