Metadata-Version: 2.1
Name: cv-parser
Version: 0.2
Summary: This package parses a Curriculum vitae yaml file and generates a pdf and web files
Home-page: https://github.com/soloidx/cv-parser
Author: Ider Delzo
Author-email: soloidx@gmail.com
License: UNKNOWN
Project-URL: Bug Tracker, https://github.com/soloidx/cv-parser/issues
Project-URL: Source Code, https://github.com/soloidx/cv-parser
Keywords: resume cv,curriculum vitae
Platform: UNKNOWN
Classifier: License :: OSI Approved :: MIT License
